{
  "title": "Post T-REST resources",
  "description": "Learn how to post value to T-REST resources on two node",
  "difficulty": "beginner",
  "time": "15 minutes",
  "details": {
    "steps": [
      {
        "title": "Step 1 - Run T-REST engine",
        "text": "step1.md"
      },
      {
        "title": "Step 2 - Develop",
        "text": "step2.md"
      },
      {
        "title": "Step 3 - Configure",
        "text": "step3.md"
      },
      {
        "title": "Step 4 - Deploy",
        "text": "step4.md"
      },
      {
        "title": "Step 5 - POST",
        "text": "step5.md"
      },
      {
        "title": "Step 6 - DELETE",
        "text": "step6.md"
      }
    ],
    "intro": {
      "text": "intro.md",
      "credits": ""
    },
    "finish": {
      "text": "finish.md"
    }
  },
  "environment": {
    "uilayout": "editor-terminal",
    "uisettings": "json"
  },
  "backend": {
    "imageid": "docker-swarm"
  }
}
